uefi_support/EfiCompressor.c
uefi_support/huff11.bin
uefi_support/EfiCompressor.cpython-310-darwin.so
uefi_support/Cab.pyi
uefi_support/LzmaCompressor.pyi
uefi_support/HuffmanCompressor.pyi
uefi_support/EfiCompressor.pyi
uefi_support/_version.py
uefi_support/__init__.py
uefi_support/Cab.c
uefi_support/huffman.py
uefi_support/LzmaCompressor.cpython-310-darwin.so
uefi_support/LzmaCompressor.c
uefi_support/Cab.cpython-310-darwin.so
uefi_support/HuffmanCompressor.c
uefi_support/py.typed
uefi_support/HuffmanCompressor.cpython-310-darwin.so
cert_uefi_support-0.9.26.dist-info/RECORD
cert_uefi_support-0.9.26.dist-info/WHEEL
cert_uefi_support-0.9.26.dist-info/top_level.txt
cert_uefi_support-0.9.26.dist-info/METADATA
cert_uefi_support-0.9.26.dist-info/licenses/LICENSE.md
