Metadata-Version: 2.4
Name: cert-uefi-support
Version: 0.9.26
Summary: A package for decompressing file formats found in UEFI distributions
Author-email: CERT Threat Analysis Team <cert@cert.org>
License-Expression: BSD-2-Clause-Patent AND LGPL-2.1 AND MIT AND LicenseRef-Custom
Project-URL: Homepage, https://github.com/cmu-sei/cert-uefi-support
Project-URL: Repository, https://github.com/cmu-sei/cert-uefi-support
Keywords: uefi,firmware,uefi-decompression,support-tools
Classifier: Development Status :: 4 - Beta
Classifier: Programming Language :: Python :: 3
Classifier: Operating System :: MacOS :: MacOS X
Classifier: Operating System :: Microsoft :: Windows
Classifier: Operating System :: POSIX :: Linux
Classifier: Topic :: Security
Classifier: Topic :: System :: Hardware
Requires-Python: >=3.10
License-File: LICENSE.md
Dynamic: license-file
